Metadata-Version: 2.4
Name: crewai-token-tracking
Version: 1.7.2
Summary: CrewAI fork with per-agent and per-task token tracking. Track token usage for each agent and task to optimize costs and performance.
Project-URL: Homepage, https://github.com/Devasy23/crewAI-telemetry
Project-URL: Documentation, https://github.com/Devasy23/crewAI-telemetry/blob/main/README.md
Project-URL: Repository, https://github.com/Devasy23/crewAI-telemetry
Project-URL: Original CrewAI, https://github.com/crewAIInc/crewAI
Author-email: Devasy Patel <patel.devasy.23@gmail.com>
Requires-Python: <3.14,>=3.10
Requires-Dist: aiosqlite~=0.21.0
Requires-Dist: appdirs~=1.4.4
Requires-Dist: chromadb~=1.1.0
Requires-Dist: click~=8.1.7
Requires-Dist: instructor>=1.3.3
Requires-Dist: json-repair~=0.25.2
Requires-Dist: json5~=0.10.0
Requires-Dist: jsonref~=1.1.0
Requires-Dist: mcp~=1.16.0
Requires-Dist: openai~=1.83.0
Requires-Dist: openpyxl~=3.1.5
Requires-Dist: opentelemetry-api~=1.34.0
Requires-Dist: opentelemetry-exporter-otlp-proto-http~=1.34.0
Requires-Dist: opentelemetry-sdk~=1.34.0
Requires-Dist: pdfplumber~=0.11.4
Requires-Dist: portalocker~=2.7.0
Requires-Dist: pydantic-settings~=2.10.1
Requires-Dist: pydantic~=2.11.9
Requires-Dist: pyjwt~=2.9.0
Requires-Dist: python-dotenv~=1.1.1
Requires-Dist: regex~=2024.9.11
Requires-Dist: tokenizers~=0.20.3
Requires-Dist: tomli-w~=1.1.0
Requires-Dist: tomli~=2.0.2
Requires-Dist: uv~=0.9.13
Provides-Extra: a2a
Requires-Dist: a2a-sdk~=0.3.10; extra == 'a2a'
Requires-Dist: aiocache[memcached,redis]~=0.12.3; extra == 'a2a'
Requires-Dist: httpx-auth~=0.23.1; extra == 'a2a'
Requires-Dist: httpx-sse~=0.4.0; extra == 'a2a'
Provides-Extra: anthropic
Requires-Dist: anthropic~=0.71.0; extra == 'anthropic'
Provides-Extra: aws
Requires-Dist: aiobotocore~=2.25.2; extra == 'aws'
Requires-Dist: boto3~=1.40.38; extra == 'aws'
Provides-Extra: azure-ai-inference
Requires-Dist: azure-ai-inference~=1.0.0b9; extra == 'azure-ai-inference'
Provides-Extra: bedrock
Requires-Dist: boto3~=1.40.45; extra == 'bedrock'
Provides-Extra: docling
Requires-Dist: docling~=2.63.0; extra == 'docling'
Provides-Extra: embeddings
Requires-Dist: tiktoken~=0.8.0; extra == 'embeddings'
Provides-Extra: google-genai
Requires-Dist: google-genai~=1.49.0; extra == 'google-genai'
Provides-Extra: litellm
Requires-Dist: litellm~=1.74.9; extra == 'litellm'
Provides-Extra: mem0
Requires-Dist: mem0ai~=0.1.94; extra == 'mem0'
Provides-Extra: openpyxl
Requires-Dist: openpyxl~=3.1.5; extra == 'openpyxl'
Provides-Extra: pandas
Requires-Dist: pandas~=2.2.3; extra == 'pandas'
Provides-Extra: qdrant
Requires-Dist: qdrant-client[fastembed]~=1.14.3; extra == 'qdrant'
Provides-Extra: tools
Requires-Dist: crewai-tools==1.7.2; extra == 'tools'
Provides-Extra: voyageai
Requires-Dist: voyageai~=0.3.5; extra == 'voyageai'
Provides-Extra: watson
Requires-Dist: ibm-watsonx-ai~=1.3.39; extra == 'watson'
